arp_to_hosts/__init__.py
arp_to_hosts/arp_to_hosts.py
arp_to_hosts/arp_to_hosts_tests.py
arp_to_hosts-0.1.6.dist-info/METADATA
arp_to_hosts-0.1.6.dist-info/WHEEL
arp_to_hosts-0.1.6.dist-info/entry_points.txt
arp_to_hosts-0.1.6.dist-info/top_level.txt
arp_to_hosts-0.1.6.dist-info/RECORD
