Metadata-Version: 2.1
Name: arp-to-hosts
Version: 0.1.6
Summary: arp-scan to /etc/hosts
Home-page: https://github.com/obradovic/arp-to-hosts
Author: Zo Obradovic
Author-email: ping@obradovic.com
License: UNKNOWN
Platform: UNKNOWN
Classifier: Programming Language :: Python :: 3
Classifier: License :: OSI Approved :: MIT License
Classifier: Operating System :: OS Independent
Requires-Dist: delegator.py
Requires-Dist: python-hosts (>=1.0.0)
Requires-Dist: validators (>=0.18.0)
